03.06/led.v
module led (
    input clk,
    input rst,
    output reg led=0
);
parameter T = 25_000_000;

reg [23:0] counter=0;
reg [3:0] n=1;
always @(posedge clk ) begin
        if (rst) begin
            counter <= 0;
            led<=1'b0;
        end else if (counter==(T/250)*n) begin
            led<=~led;
        end else if (counter==((T/250)*n)-(T/250)) begin
             led<=1'b0;
             n<=n+1;
        end else if (counter==T) begin
            counter<=0;
            n<=0;
        end else counter<=counter+1'b1;          
end
    
endmodule

03.06/tb.v
 `timescale 1 ns/1 ps
module tb();

reg clk;
reg rst;
wire led;


led l(.clk(clk), .rst(rst), .led(led));

initial begin
	$dumpfile("v.vcd");
    $dumpvars();

	
end

initial begin 
	clk = 1'b0;
	rst = 1'b1;
    #10;
    rst = 1'b0;

end

always #3 clk = ~clk;

initial begin
repeat (100) begin
    @(posedge clk);
    #1;
    $display ("Time = %0t, LEDs = %b", $time, led);
end
end
initial begin
    #9000;
   
    $finish;
end

endmodule

03.06/v.vcd
$date
	Sun Jun  4 16:23:26 2023
$end
$version
	Icarus Verilog
$end
$timescale
	1ps
$end
$scope module tb $end
$var wire 1 ! led $end
$var reg 1 " clk $end
$var reg 1 # rst $end
$scope module l $end
$var wire 1 " clk $end
$var wire 1 # rst $end
$var reg 24 $ counter [23:0] $end
$var reg 1 ! led $end
$var reg 4 % n [3:0] $end
$upscope $end
$upscope $end
$enddefinitions $end
#0
$dumpvars
b1 %
b0 $
1#
0"
0!
$end
#3000
1"
#6000
0"
#9000
1"
#10000
0#
#12000
0"
#15000
b10 %
1"
#18000
0"
#21000
b1 $
1"
#24000
0"
#27000
b10 $
1"
#30000
0"
#33000
b11 $
1"
#36000
0"
#39000
b100 $
1"
#42000
0"
#45000
b101 $
1"
#48000
0"
#51000
b110 $
1"
#54000
0"
#57000
b111 $
1"
#60000
0"
#63000
b1000 $
1"
#66000
0"
#69000
b1001 $
1"
#72000
0"
#75000
b1010 $
1"
#78000
0"
#81000
b1011 $
1"
#84000
0"
#87000
b1100 $
1"
#90000
0"
#93000
b1101 $
1"
#96000
0"
#99000
b1110 $
1"
#102000
0"
#105000
b1111 $
1"
#108000
0"
#111000
b10000 $
1"
#114000
0"
#117000
b10001 $
1"
#120000
0"
#123000
b10010 $
1"
#126000
0"
#129000
b10011 $
1"
#132000
0"
#135000
b10100 $
1"
#138000
0"
#141000
b10101 $
1"
#144000
0"
#147000
b10110 $
1"
#150000
0"
#153000
b10111 $
1"
#156000
0"
#159000
b11000 $
1"
#162000
0"
#165000
b11001 $
1"
#168000
0"
#171000
b11010 $
1"
#174000
0"
#177000
b11011 $
1"
#180000
0"
#183000
b11100 $
1"
#186000
0"
#189000
b11101 $
1"
#192000
0"
#195000
b11110 $
1"
#198000
0"
#201000
b11111 $
1"
#204000
0"
#207000
b100000 $
1"
#210000
0"
#213000
b100001 $
1"
#216000
0"
#219000
b100010 $
1"
#222000
0"
#225000
b100011 $
1"
#228000
0"
#231000
b100100 $
1"
#234000
0"
#237000
b100101 $
1"
#240000
0"
#243000
b100110 $
1"
#246000
0"
#249000
b100111 $
1"
#252000
0"
#255000
b101000 $
1"
#258000
0"
#261000
b101001 $
1"
#264000
0"
#267000
b101010 $
1"
#270000
0"
#273000
b101011 $
1"
#276000
0"
#279000
b101100 $
1"
#282000
0"
#285000
b101101 $
1"
#288000
0"
#291000
b101110 $
1"
#294000
0"
#297000
b101111 $
1"
#300000
0"
#303000
b110000 $
1"
#306000
0"
#309000
b110001 $
1"
#312000
0"
#315000
b110010 $
1"
#318000
0"
#321000
b110011 $
1"
#324000
0"
#327000
b110100 $
1"
#330000
0"
#333000
b110101 $
1"
#336000
0"
#339000
b110110 $
1"
#342000
0"
#345000
b110111 $
1"
#348000
0"
#351000
b111000 $
1"
#354000
0"
#357000
b111001 $
1"
#360000
0"
#363000
b111010 $
1"
#366000
0"
#369000
b111011 $
1"
#372000
0"
#375000
b111100 $
1"
#378000
0"
#381000
b111101 $
1"
#384000
0"
#387000
b111110 $
1"
#390000
0"
#393000
b111111 $
1"
#396000
0"
#399000
b1000000 $
1"
#402000
0"
#405000
b1000001 $
1"
#408000
0"
#411000
b1000010 $
1"
#414000
0"
#417000
b1000011 $
1"
#420000
0"
#423000
b1000100 $
1"
#426000
0"
#429000
b1000101 $
1"
#432000
0"
#435000
b1000110 $
1"
#438000
0"
#441000
b1000111 $
1"
#444000
0"
#447000
b1001000 $
1"
#450000
0"
#453000
b1001001 $
1"
#456000
0"
#459000
b1001010 $
1"
#462000
0"
#465000
b1001011 $
1"
#468000
0"
#471000
b1001100 $
1"
#474000
0"
#477000
b1001101 $
1"
#480000
0"
#483000
b1001110 $
1"
#486000
0"
#489000
b1001111 $
1"
#492000
0"
#495000
b1010000 $
1"
#498000
0"
#501000
b1010001 $
1"
#504000
0"
#507000
b1010010 $
1"
#510000
0"
#513000
b1010011 $
1"
#516000
0"
#519000
b1010100 $
1"
#522000
0"
#525000
b1010101 $
1"
#528000
0"
#531000
b1010110 $
1"
#534000
0"
#537000
b1010111 $
1"
#540000
0"
#543000
b1011000 $
1"
#546000
0"
#549000
b1011001 $
1"
#552000
0"
#555000
b1011010 $
1"
#558000
0"
#561000
b1011011 $
1"
#564000
0"
#567000
b1011100 $
1"
#570000
0"
#573000
b1011101 $
1"
#576000
0"
#579000
b1011110 $
1"
#582000
0"
#585000
b1011111 $
1"
#588000
0"
#591000
b1100000 $
1"
#594000
0"
#597000
b1100001 $
1"
#600000
0"
#603000
b1100010 $
1"
#606000
0"
#609000
b1100011 $
1"
#612000
0"
#615000
b1100100 $
1"
#618000
0"
#621000
b1100101 $
1"
#624000
0"
#627000
b1100110 $
1"
#630000
0"
#633000
b1100111 $
1"
#636000
0"
#639000
b1101000 $
1"
#642000
0"
#645000
b1101001 $
1"
#648000
0"
#651000
b1101010 $
1"
#654000
0"
#657000
b1101011 $
1"
#660000
0"
#663000
b1101100 $
1"
#666000
0"
#669000
b1101101 $
1"
#672000
0"
#675000
b1101110 $
1"
#678000
0"
#681000
b1101111 $
1"
#684000
0"
#687000
b1110000 $
1"
#690000
0"
#693000
b1110001 $
1"
#696000
0"
#699000
b1110010 $
1"
#702000
0"
#705000
b1110011 $
1"
#708000
0"
#711000
b1110100 $
1"
#714000
0"
#717000
b1110101 $
1"
#720000
0"
#723000
b1110110 $
1"
#726000
0"
#729000
b1110111 $
1"
#732000
0"
#735000
b1111000 $
1"
#738000
0"
#741000
b1111001 $
1"
#744000
0"
#747000
b1111010 $
1"
#750000
0"
#753000
b1111011 $
1"
#756000
0"
#759000
b1111100 $
1"
#762000
0"
#765000
b1111101 $
1"
#768000
0"
#771000
b1111110 $
1"
#774000
0"
#777000
b1111111 $
1"
#780000
0"
#783000
b10000000 $
1"
#786000
0"
#789000
b10000001 $
1"
#792000
0"
#795000
b10000010 $
1"
#798000
0"
#801000
b10000011 $
1"
#804000
0"
#807000
b10000100 $
1"
#810000
0"
#813000
b10000101 $
1"
#816000
0"
#819000
b10000110 $
1"
#822000
0"
#825000
b10000111 $
1"
#828000
0"
#831000
b10001000 $
1"
#834000
0"
#837000
b10001001 $
1"
#840000
0"
#843000
b10001010 $
1"
#846000
0"
#849000
b10001011 $
1"
#852000
0"
#855000
b10001100 $
1"
#858000
0"
#861000
b10001101 $
1"
#864000
0"
#867000
b10001110 $
1"
#870000
0"
#873000
b10001111 $
1"
#876000
0"
#879000
b10010000 $
1"
#882000
0"
#885000
b10010001 $
1"
#888000
0"
#891000
b10010010 $
1"
#894000
0"
#897000
b10010011 $
1"
#900000
0"
#903000
b10010100 $
1"
#906000
0"
#909000
b10010101 $
1"
#912000
0"
#915000
b10010110 $
1"
#918000
0"
#921000
b10010111 $
1"
#924000
0"
#927000
b10011000 $
1"
#930000
0"
#933000
b10011001 $
1"
#936000
0"
#939000
b10011010 $
1"
#942000
0"
#945000
b10011011 $
1"
#948000
0"
#951000
b10011100 $
1"
#954000
0"
#957000
b10011101 $
1"
#960000
0"
#963000
b10011110 $
1"
#966000
0"
#969000
b10011111 $
1"
#972000
0"
#975000
b10100000 $
1"
#978000
0"
#981000
b10100001 $
1"
#984000
0"
#987000
b10100010 $
1"
#990000
0"
#993000
b10100011 $
1"
#996000
0"
#999000
b10100100 $
1"
#1002000
0"
#1005000
b10100101 $
1"
#1008000
0"
#1011000
b10100110 $
1"
#1014000
0"
#1017000
b10100111 $
1"
#1020000
0"
#1023000
b10101000 $
1"
#1026000
0"
#1029000
b10101001 $
1"
#1032000
0"
#1035000
b10101010 $
1"
#1038000
0"
#1041000
b10101011 $
1"
#1044000
0"
#1047000
b10101100 $
1"
#1050000
0"
#1053000
b10101101 $
1"
#1056000
0"
#1059000
b10101110 $
1"
#1062000
0"
#1065000
b10101111 $
1"
#1068000
0"
#1071000
b10110000 $
1"
#1074000
0"
#1077000
b10110001 $
1"
#1080000
0"
#1083000
b10110010 $
1"
#1086000
0"
#1089000
b10110011 $
1"
#1092000
0"
#1095000
b10110100 $
1"
#1098000
0"
#1101000
b10110101 $
1"
#1104000
0"
#1107000
b10110110 $
1"
#1110000
0"
#1113000
b10110111 $
1"
#1116000
0"
#1119000
b10111000 $
1"
#1122000
0"
#1125000
b10111001 $
1"
#1128000
0"
#1131000
b10111010 $
1"
#1134000
0"
#1137000
b10111011 $
1"
#1140000
0"
#1143000
b10111100 $
1"
#1146000
0"
#1149000
b10111101 $
1"
#1152000
0"
#1155000
b10111110 $
1"
#1158000
0"
#1161000
b10111111 $
1"
#1164000
0"
#1167000
b11000000 $
1"
#1170000
0"
#1173000
b11000001 $
1"
#1176000
0"
#1179000
b11000010 $
1"
#1182000
0"
#1185000
b11000011 $
1"
#1188000
0"
#1191000
b11000100 $
1"
#1194000
0"
#1197000
b11000101 $
1"
#1200000
0"
#1203000
b11000110 $
1"
#1206000
0"
#1209000
b11000111 $
1"
#1212000
0"
#1215000
b11001000 $
1"
#1218000
0"
#1221000
b11001001 $
1"
#1224000
0"
#1227000
b11001010 $
1"
#1230000
0"
#1233000
b11001011 $
1"
#1236000
0"
#1239000
b11001100 $
1"
#1242000
0"
#1245000
b11001101 $
1"
#1248000
0"
#1251000
b11001110 $
1"
#1254000
0"
#1257000
b11001111 $
1"
#1260000
0"
#1263000
b11010000 $
1"
#1266000
0"
#1269000
b11010001 $
1"
#1272000
0"
#1275000
b11010010 $
1"
#1278000
0"
#1281000
b11010011 $
1"
#1284000
0"
#1287000
b11010100 $
1"
#1290000
0"
#1293000
b11010101 $
1"
#1296000
0"
#1299000
b11010110 $
1"
#1302000
0"
#1305000
b11010111 $
1"
#1308000
0"
#1311000
b11011000 $
1"
#1314000
0"
#1317000
b11011001 $
1"
#1320000
0"
#1323000
b11011010 $
1"
#1326000
0"
#1329000
b11011011 $
1"
#1332000
0"
#1335000
b11011100 $
1"
#1338000
0"
#1341000
b11011101 $
1"
#1344000
0"
#1347000
b11011110 $
1"
#1350000
0"
#1353000
b11011111 $
1"
#1356000
0"
#1359000
b11100000 $
1"
#1362000
0"
#1365000
b11100001 $
1"
#1368000
0"
#1371000
b11100010 $
1"
#1374000
0"
#1377000
b11100011 $
1"
#1380000
0"
#1383000
b11100100 $
1"
#1386000
0"
#1389000
b11100101 $
1"
#1392000
0"
#1395000
b11100110 $
1"
#1398000
0"
#1401000
b11100111 $
1"
#1404000
0"
#1407000
b11101000 $
1"
#1410000
0"
#1413000
b11101001 $
1"
#1416000
0"
#1419000
b11101010 $
1"
#1422000
0"
#1425000
b11101011 $
1"
#1428000
0"
#1431000
b11101100 $
1"
#1434000
0"
#1437000
b11101101 $
1"
#1440000
0"
#1443000
b11101110 $
1"
#1446000
0"
#1449000
b11101111 $
1"
#1452000
0"
#1455000
b11110000 $
1"
#1458000
0"
#1461000
b11110001 $
1"
#1464000
0"
#1467000
b11110010 $
1"
#1470000
0"
#1473000
b11110011 $
1"
#1476000
0"
#1479000
b11110100 $
1"
#1482000
0"
#1485000
b11110101 $
1"
#1488000
0"
#1491000
b11110110 $
1"
#1494000
0"
#1497000
b11110111 $
1"
#1500000
0"
#1503000
b11111000 $
1"
#1506000
0"
#1509000
b11111001 $
1"
#1512000
0"
#1515000
b11111010 $
1"
#1518000
0"
#1521000
b11111011 $
1"
#1524000
0"
#1527000
b11111100 $
1"
#1530000
0"
#1533000
b11111101 $
1"
#1536000
0"
#1539000
b11111110 $
1"
#1542000
0"
#1545000
b11111111 $
1"
#1548000
0"
#1551000
b100000000 $
1"
#1554000
0"
#1557000
b100000001 $
1"
#1560000
0"
#1563000
b100000010 $
1"
#1566000
0"
#1569000
b100000011 $
1"
#1572000
0"
#1575000
b100000100 $
1"
#1578000
0"
#1581000
b100000101 $
1"
#1584000
0"
#1587000
b100000110 $
1"
#1590000
0"
#1593000
b100000111 $
1"
#1596000
0"
#1599000
b100001000 $
1"
#1602000
0"
#1605000
b100001001 $
1"
#1608000
0"
#1611000
b100001010 $
1"
#1614000
0"
#1617000
b100001011 $
1"
#1620000
0"
#1623000
b100001100 $
1"
#1626000
0"
#1629000
b100001101 $
1"
#1632000
0"
#1635000
b100001110 $
1"
#1638000
0"
#1641000
b100001111 $
1"
#1644000
0"
#1647000
b100010000 $
1"
#1650000
0"
#1653000
b100010001 $
1"
#1656000
0"
#1659000
b100010010 $
1"
#1662000
0"
#1665000
b100010011 $
1"
#1668000
0"
#1671000
b100010100 $
1"
#1674000
0"
#1677000
b100010101 $
1"
#1680000
0"
#1683000
b100010110 $
1"
#1686000
0"
#1689000
b100010111 $
1"
#1692000
0"
#1695000
b100011000 $
1"
#1698000
0"
#1701000
b100011001 $
1"
#1704000
0"
#1707000
b100011010 $
1"
#1710000
0"
#1713000
b100011011 $
1"
#1716000
0"
#1719000
b100011100 $
1"
#1722000
0"
#1725000
b100011101 $
1"
#1728000
0"
#1731000
b100011110 $
1"
#1734000
0"
#1737000
b100011111 $
1"
#1740000
0"
#1743000
b100100000 $
1"
#1746000
0"
#1749000
b100100001 $
1"
#1752000
0"
#1755000
b100100010 $
1"
#1758000
0"
#1761000
b100100011 $
1"
#1764000
0"
#1767000
b100100100 $
1"
#1770000
0"
#1773000
b100100101 $
1"
#1776000
0"
#1779000
b100100110 $
1"
#1782000
0"
#1785000
b100100111 $
1"
#1788000
0"
#1791000
b100101000 $
1"
#1794000
0"
#1797000
b100101001 $
1"
#1800000
0"
#1803000
b100101010 $
1"
#1806000
0"
#1809000
b100101011 $
1"
#1812000
0"
#1815000
b100101100 $
1"
#1818000
0"
#1821000
b100101101 $
1"
#1824000
0"
#1827000
b100101110 $
1"
#1830000
0"
#1833000
b100101111 $
1"
#1836000
0"
#1839000
b100110000 $
1"
#1842000
0"
#1845000
b100110001 $
1"
#1848000
0"
#1851000
b100110010 $
1"
#1854000
0"
#1857000
b100110011 $
1"
#1860000
0"
#1863000
b100110100 $
1"
#1866000
0"
#1869000
b100110101 $
1"
#1872000
0"
#1875000
b100110110 $
1"
#1878000
0"
#1881000
b100110111 $
1"
#1884000
0"
#1887000
b100111000 $
1"
#1890000
0"
#1893000
b100111001 $
1"
#1896000
0"
#1899000
b100111010 $
1"
#1902000
0"
#1905000
b100111011 $
1"
#1908000
0"
#1911000
b100111100 $
1"
#1914000
0"
#1917000
b100111101 $
1"
#1920000
0"
#1923000
b100111110 $
1"
#1926000
0"
#1929000
b100111111 $
1"
#1932000
0"
#1935000
b101000000 $
1"
#1938000
0"
#1941000
b101000001 $
1"
#1944000
0"
#1947000
b101000010 $
1"
#1950000
0"
#1953000
b101000011 $
1"
#1956000
0"
#1959000
b101000100 $
1"
#1962000
0"
#1965000
b101000101 $
1"
#1968000
0"
#1971000
b101000110 $
1"
#1974000
0"
#1977000
b101000111 $
1"
#1980000
0"
#1983000
b101001000 $
1"
#1986000
0"
#1989000
b101001001 $
1"
#1992000
0"
#1995000
b101001010 $
1"
#1998000
0"
#2001000
b101001011 $
1"
#2004000
0"
#2007000
b101001100 $
1"
#2010000
0"
#2013000
b101001101 $
1"
#2016000
0"
#2019000
b101001110 $
1"
#2022000
0"
#2025000
b101001111 $
1"
#2028000
0"
#2031000
b101010000 $
1"
#2034000
0"
#2037000
b101010001 $
1"
#2040000
0"
#2043000
b101010010 $
1"
#2046000
0"
#2049000
b101010011 $
1"
#2052000
0"
#2055000
b101010100 $
1"
#2058000
0"
#2061000
b101010101 $
1"
#2064000
0"
#2067000
b101010110 $
1"
#2070000
0"
#2073000
b101010111 $
1"
#2076000
0"
#2079000
b101011000 $
1"
#2082000
0"
#2085000
b101011001 $
1"
#2088000
0"
#2091000
b101011010 $
1"
#2094000
0"
#2097000
b101011011 $
1"
#2100000
0"
#2103000
b101011100 $
1"
#2106000
0"
#2109000
b101011101 $
1"
#2112000
0"
#2115000
b101011110 $
1"
#2118000
0"
#2121000
b101011111 $
1"
#2124000
0"
#2127000
b101100000 $
1"
#2130000
0"
#2133000
b101100001 $
1"
#2136000
0"
#2139000
b101100010 $
1"
#2142000
0"
#2145000
b101100011 $
1"
#2148000
0"
#2151000
b101100100 $
1"
#2154000
0"
#2157000
b101100101 $
1"
#2160000
0"
#2163000
b101100110 $
1"
#2166000
0"
#2169000
b101100111 $
1"
#2172000
0"
#2175000
b101101000 $
1"
#2178000
0"
#2181000
b101101001 $
1"
#2184000
0"
#2187000
b101101010 $
1"
#2190000
0"
#2193000
b101101011 $
1"
#2196000
0"
#2199000
b101101100 $
1"
#2202000
0"
#2205000
b101101101 $
1"
#2208000
0"
#2211000
b101101110 $
1"
#2214000
0"
#2217000
b101101111 $
1"
#2220000
0"
#2223000
b101110000 $
1"
#2226000
0"
#2229000
b101110001 $
1"
#2232000
0"
#2235000
b101110010 $
1"
#2238000
0"
#2241000
b101110011 $
1"
#2244000
0"
#2247000
b101110100 $
1"
#2250000
0"
#2253000
b101110101 $
1"
#2256000
0"
#2259000
b101110110 $
1"
#2262000
0"
#2265000
b101110111 $
1"
#2268000
0"
#2271000
b101111000 $
1"
#2274000
0"
#2277000
b101111001 $
1"
#2280000
0"
#2283000
b101111010 $
1"
#2286000
0"
#2289000
b101111011 $
1"
#2292000
0"
#2295000
b101111100 $
1"
#2298000
0"
#2301000
b101111101 $
1"
#2304000
0"
#2307000
b101111110 $
1"
#2310000
0"
#2313000
b101111111 $
1"
#2316000
0"
#2319000
b110000000 $
1"
#2322000
0"
#2325000
b110000001 $
1"
#2328000
0"
#2331000
b110000010 $
1"
#2334000
0"
#2337000
b110000011 $
1"
#2340000
0"
#2343000
b110000100 $
1"
#2346000
0"
#2349000
b110000101 $
1"
#2352000
0"
#2355000
b110000110 $
1"
#2358000
0"
#2361000
b110000111 $
1"
#2364000
0"
#2367000
b110001000 $
1"
#2370000
0"
#2373000
b110001001 $
1"
#2376000
0"
#2379000
b110001010 $
1"
#2382000
0"
#2385000
b110001011 $
1"
#2388000
0"
#2391000
b110001100 $
1"
#2394000
0"
#2397000
b110001101 $
1"
#2400000
0"
#2403000
b110001110 $
1"
#2406000
0"
#2409000
b110001111 $
1"
#2412000
0"
#2415000
b110010000 $
1"
#2418000
0"
#2421000
b110010001 $
1"
#2424000
0"
#2427000
b110010010 $
1"
#2430000
0"
#2433000
b110010011 $
1"
#2436000
0"
#2439000
b110010100 $
1"
#2442000
0"
#2445000
b110010101 $
1"
#2448000
0"
#2451000
b110010110 $
1"
#2454000
0"
#2457000
b110010111 $
1"
#2460000
0"
#2463000
b110011000 $
1"
#2466000
0"
#2469000
b110011001 $
1"
#2472000
0"
#2475000
b110011010 $
1"
#2478000
0"
#2481000
b110011011 $
1"
#2484000
0"
#2487000
b110011100 $
1"
#2490000
0"
#2493000
b110011101 $
1"
#2496000
0"
#2499000
b110011110 $
1"
#2502000
0"
#2505000
b110011111 $
1"
#2508000
0"
#2511000
b110100000 $
1"
#2514000
0"
#2517000
b110100001 $
1"
#2520000
0"
#2523000
b110100010 $
1"
#2526000
0"
#2529000
b110100011 $
1"
#2532000
0"
#2535000
b110100100 $
1"
#2538000
0"
#2541000
b110100101 $
1"
#2544000
0"
#2547000
b110100110 $
1"
#2550000
0"
#2553000
b110100111 $
1"
#2556000
0"
#2559000
b110101000 $
1"
#2562000
0"
#2565000
b110101001 $
1"
#2568000
0"
#2571000
b110101010 $
1"
#2574000
0"
#2577000
b110101011 $
1"
#2580000
0"
#2583000
b110101100 $
1"
#2586000
0"
#2589000
b110101101 $
1"
#2592000
0"
#2595000
b110101110 $
1"
#2598000
0"
#2601000
b110101111 $
1"
#2604000
0"
#2607000
b110110000 $
1"
#2610000
0"
#2613000
b110110001 $
1"
#2616000
0"
#2619000
b110110010 $
1"
#2622000
0"
#2625000
b110110011 $
1"
#2628000
0"
#2631000
b110110100 $
1"
#2634000
0"
#2637000
b110110101 $
1"
#2640000
0"
#2643000
b110110110 $
1"
#2646000
0"
#2649000
b110110111 $
1"
#2652000
0"
#2655000
b110111000 $
1"
#2658000
0"
#2661000
b110111001 $
1"
#2664000
0"
#2667000
b110111010 $
1"
#2670000
0"
#2673000
b110111011 $
1"
#2676000
0"
#2679000
b110111100 $
1"
#2682000
0"
#2685000
b110111101 $
1"
#2688000
0"
#2691000
b110111110 $
1"
#2694000
0"
#2697000
b110111111 $
1"
#2700000
0"
#2703000
b111000000 $
1"
#2706000
0"
#2709000
b111000001 $
1"
#2712000
0"
#2715000
b111000010 $
1"
#2718000
0"
#2721000
b111000011 $
1"
#2724000
0"
#2727000
b111000100 $
1"
#2730000
0"
#2733000
b111000101 $
1"
#2736000
0"
#2739000
b111000110 $
1"
#2742000
0"
#2745000
b111000111 $
1"
#2748000
0"
#2751000
b111001000 $
1"
#2754000
0"
#2757000
b111001001 $
1"
#2760000
0"
#2763000
b111001010 $
1"
#2766000
0"
#2769000
b111001011 $
1"
#2772000
0"
#2775000
b111001100 $
1"
#2778000
0"
#2781000
b111001101 $
1"
#2784000
0"
#2787000
b111001110 $
1"
#2790000
0"
#2793000
b111001111 $
1"
#2796000
0"
#2799000
b111010000 $
1"
#2802000
0"
#2805000
b111010001 $
1"
#2808000
0"
#2811000
b111010010 $
1"
#2814000
0"
#2817000
b111010011 $
1"
#2820000
0"
#2823000
b111010100 $
1"
#2826000
0"
#2829000
b111010101 $
1"
#2832000
0"
#2835000
b111010110 $
1"
#2838000
0"
#2841000
b111010111 $
1"
#2844000
0"
#2847000
b111011000 $
1"
#2850000
0"
#2853000
b111011001 $
1"
#2856000
0"
#2859000
b111011010 $
1"
#2862000
0"
#2865000
b111011011 $
1"
#2868000
0"
#2871000
b111011100 $
1"
#2874000
0"
#2877000
b111011101 $
1"
#2880000
0"
#2883000
b111011110 $
1"
#2886000
0"
#2889000
b111011111 $
1"
#2892000
0"
#2895000
b111100000 $
1"
#2898000
0"
#2901000
b111100001 $
1"
#2904000
0"
#2907000
b111100010 $
1"
#2910000
0"
#2913000
b111100011 $
1"
#2916000
0"
#2919000
b111100100 $
1"
#2922000
0"
#2925000
b111100101 $
1"
#2928000
0"
#2931000
b111100110 $
1"
#2934000
0"
#2937000
b111100111 $
1"
#2940000
0"
#2943000
b111101000 $
1"
#2946000
0"
#2949000
b111101001 $
1"
#2952000
0"
#2955000
b111101010 $
1"
#2958000
0"
#2961000
b111101011 $
1"
#2964000
0"
#2967000
b111101100 $
1"
#2970000
0"
#2973000
b111101101 $
1"
#2976000
0"
#2979000
b111101110 $
1"
#2982000
0"
#2985000
b111101111 $
1"
#2988000
0"
#2991000
b111110000 $
1"
#2994000
0"
#2997000
b111110001 $
1"
#3000000
0"
#3003000
b111110010 $
1"
#3006000
0"
#3009000
b111110011 $
1"
#3012000
0"
#3015000
b111110100 $
1"
#3018000
0"
#3021000
b111110101 $
1"
#3024000
0"
#3027000
b111110110 $
1"
#3030000
0"
#3033000
b111110111 $
1"
#3036000
0"
#3039000
b111111000 $
1"
#3042000
0"
#3045000
b111111001 $
1"
#3048000
0"
#3051000
b111111010 $
1"
#3054000
0"
#3057000
b111111011 $
1"
#3060000
0"
#3063000
b111111100 $
1"
#3066000
0"
#3069000
b111111101 $
1"
#3072000
0"
#3075000
b111111110 $
1"
#3078000
0"
#3081000
b111111111 $
1"
#3084000
0"
#3087000
b1000000000 $
1"
#3090000
0"
#3093000
b1000000001 $
1"
#3096000
0"
#3099000
b1000000010 $
1"
#3102000
0"
#3105000
b1000000011 $
1"
#3108000
0"
#3111000
b1000000100 $
1"
#3114000
0"
#3117000
b1000000101 $
1"
#3120000
0"
#3123000
b1000000110 $
1"
#3126000
0"
#3129000
b1000000111 $
1"
#3132000
0"
#3135000
b1000001000 $
1"
#3138000
0"
#3141000
b1000001001 $
1"
#3144000
0"
#3147000
b1000001010 $
1"
#3150000
0"
#3153000
b1000001011 $
1"
#3156000
0"
#3159000
b1000001100 $
1"
#3162000
0"
#3165000
b1000001101 $
1"
#3168000
0"
#3171000
b1000001110 $
1"
#3174000
0"
#3177000
b1000001111 $
1"
#3180000
0"
#3183000
b1000010000 $
1"
#3186000
0"
#3189000
b1000010001 $
1"
#3192000
0"
#3195000
b1000010010 $
1"
#3198000
0"
#3201000
b1000010011 $
1"
#3204000
0"
#3207000
b1000010100 $
1"
#3210000
0"
#3213000
b1000010101 $
1"
#3216000
0"
#3219000
b1000010110 $
1"
#3222000
0"
#3225000
b1000010111 $
1"
#3228000
0"
#3231000
b1000011000 $
1"
#3234000
0"
#3237000
b1000011001 $
1"
#3240000
0"
#3243000
b1000011010 $
1"
#3246000
0"
#3249000
b1000011011 $
1"
#3252000
0"
#3255000
b1000011100 $
1"
#3258000
0"
#3261000
b1000011101 $
1"
#3264000
0"
#3267000
b1000011110 $
1"
#3270000
0"
#3273000
b1000011111 $
1"
#3276000
0"
#3279000
b1000100000 $
1"
#3282000
0"
#3285000
b1000100001 $
1"
#3288000
0"
#3291000
b1000100010 $
1"
#3294000
0"
#3297000
b1000100011 $
1"
#3300000
0"
#3303000
b1000100100 $
1"
#3306000
0"
#3309000
b1000100101 $
1"
#3312000
0"
#3315000
b1000100110 $
1"
#3318000
0"
#3321000
b1000100111 $
1"
#3324000
0"
#3327000
b1000101000 $
1"
#3330000
0"
#3333000
b1000101001 $
1"
#3336000
0"
#3339000
b1000101010 $
1"
#3342000
0"
#3345000
b1000101011 $
1"
#3348000
0"
#3351000
b1000101100 $
1"
#3354000
0"
#3357000
b1000101101 $
1"
#3360000
0"
#3363000
b1000101110 $
1"
#3366000
0"
#3369000
b1000101111 $
1"
#3372000
0"
#3375000
b1000110000 $
1"
#3378000
0"
#3381000
b1000110001 $
1"
#3384000
0"
#3387000
b1000110010 $
1"
#3390000
0"
#3393000
b1000110011 $
1"
#3396000
0"
#3399000
b1000110100 $
1"
#3402000
0"
#3405000
b1000110101 $
1"
#3408000
0"
#3411000
b1000110110 $
1"
#3414000
0"
#3417000
b1000110111 $
1"
#3420000
0"
#3423000
b1000111000 $
1"
#3426000
0"
#3429000
b1000111001 $
1"
#3432000
0"
#3435000
b1000111010 $
1"
#3438000
0"
#3441000
b1000111011 $
1"
#3444000
0"
#3447000
b1000111100 $
1"
#3450000
0"
#3453000
b1000111101 $
1"
#3456000
0"
#3459000
b1000111110 $
1"
#3462000
0"
#3465000
b1000111111 $
1"
#3468000
0"
#3471000
b1001000000 $
1"
#3474000
0"
#3477000
b1001000001 $
1"
#3480000
0"
#3483000
b1001000010 $
1"
#3486000
0"
#3489000
b1001000011 $
1"
#3492000
0"
#3495000
b1001000100 $
1"
#3498000
0"
#3501000
b1001000101 $
1"
#3504000
0"
#3507000
b1001000110 $
1"
#3510000
0"
#3513000
b1001000111 $
1"
#3516000
0"
#3519000
b1001001000 $
1"
#3522000
0"
#3525000
b1001001001 $
1"
#3528000
0"
#3531000
b1001001010 $
1"
#3534000
0"
#3537000
b1001001011 $
1"
#3540000
0"
#3543000
b1001001100 $
1"
#3546000
0"
#3549000
b1001001101 $
1"
#3552000
0"
#3555000
b1001001110 $
1"
#3558000
0"
#3561000
b1001001111 $
1"
#3564000
0"
#3567000
b1001010000 $
1"
#3570000
0"
#3573000
b1001010001 $
1"
#3576000
0"
#3579000
b1001010010 $
1"
#3582000
0"
#3585000
b1001010011 $
1"
#3588000
0"
#3591000
b1001010100 $
1"
#3594000
0"
#3597000
b1001010101 $
1"
#3600000
0"
#3603000
b1001010110 $
1"
#3606000
0"
#3609000
b1001010111 $
1"
#3612000
0"
#3615000
b1001011000 $
1"
#3618000
0"
#3621000
b1001011001 $
1"
#3624000
0"
#3627000
b1001011010 $
1"
#3630000
0"
#3633000
b1001011011 $
1"
#3636000
0"
#3639000
b1001011100 $
1"
#3642000
0"
#3645000
b1001011101 $
1"
#3648000
0"
#3651000
b1001011110 $
1"
#3654000
0"
#3657000
b1001011111 $
1"
#3660000
0"
#3663000
b1001100000 $
1"
#3666000
0"
#3669000
b1001100001 $
1"
#3672000
0"
#3675000
b1001100010 $
1"
#3678000
0"
#3681000
b1001100011 $
1"
#3684000
0"
#3687000
b1001100100 $
1"
#3690000
0"
#3693000
b1001100101 $
1"
#3696000
0"
#3699000
b1001100110 $
1"
#3702000
0"
#3705000
b1001100111 $
1"
#3708000
0"
#3711000
b1001101000 $
1"
#3714000
0"
#3717000
b1001101001 $
1"
#3720000
0"
#3723000
b1001101010 $
1"
#3726000
0"
#3729000
b1001101011 $
1"
#3732000
0"
#3735000
b1001101100 $
1"
#3738000
0"
#3741000
b1001101101 $
1"
#3744000
0"
#3747000
b1001101110 $
1"
#3750000
0"
#3753000
b1001101111 $
1"
#3756000
0"
#3759000
b1001110000 $
1"
#3762000
0"
#3765000
b1001110001 $
1"
#3768000
0"
#3771000
b1001110010 $
1"
#3774000
0"
#3777000
b1001110011 $
1"
#3780000
0"
#3783000
b1001110100 $
1"
#3786000
0"
#3789000
b1001110101 $
1"
#3792000
0"
#3795000
b1001110110 $
1"
