01.06/deb.v
module debounce (clk, rst, button, button_out);

input clk;
input rst;

input button;
output button_out;

reg  [17:0] counter;
wire [17:0] counter_nxt;
wire full;

assign full = (counter == 18'd250000);
assign counter_nxt = (button) ? (~full ? counter + {{17{1'b0}}, 1'b1} : 18'd250000) : {18{1'b0}};
assign button_out = full;

always @(posedge clk) begin
    if (rst) counter <= {18{1'b0}};
    else     counter <= counter_nxt;
end

endmodule

01.06/seg.v
module seg(
    input  clk,
    input  reset,
    input button,
    output reg [6:0] segOut
);
    reg dff_1;
    reg dff_2;
    wire change;
    wire button_out;

    assign change = dff_1 & ~dff_2;

    debounce debounce_i (   .clk(clk),
           .rst(rst),
           .button(button),
           .button_out(button_out)
    );

    reg [3:0] count;

    reg [23:0] timer=0;


    // DFF_1
always @(posedge clk) begin
    if (rst) dff_1 <= 1'b0;
    else     dff_1 <= button_out;
end

// DFF_2
always @(posedge clk) begin
    if (rst) dff_2 <= 1'b0;
    else     dff_2 <= dff_1;
end




    always @(posedge clk or posedge reset) begin
        if (reset) begin
            count <= 0;
        
        end  else if (timer==12_500_000) begin
             count <= count + 1'b1;
             timer<=0;
        end  else if (change) begin
            count<=count - 1;
        end else timer<=timer+1'b1;
           
    end

    always @(count) begin
        case(count)
            4'd0: segOut = 7'b1000000;  // 0
            4'd1: segOut = 7'b1111001;  // 1
            4'd2: segOut = 7'b0100100;  // 2
            4'd3: segOut = 7'b0110000;  // 3
            4'd4: segOut = 7'b0011001;  // 4
            4'd5: segOut = 7'b0010010;  // 5
            4'd6: segOut = 7'b0000010;  // 6
            4'd7: segOut = 7'b1111000;  // 7
            4'd8: segOut = 7'b0000000;  // 8
            4'd9: segOut = 7'b0010000;  // 9
            default: segOut = 7'b1111111; 
        endcase
    end

endmodule

01.06/tb.v
`timescale 1 ns/1 ps
module tb();

reg clk;
reg rst;
wire [6:0] seg;

seg s(.clk(clk), .segOut(seg), .reset(rst));

initial begin
	$dumpfile("v.vcd");
    $dumpvars();

	
end

initial begin 
	clk = 1'b0;
	rst = 1'b1;
    #10;
    rst = 1'b0;

end

always #3 clk = ~clk;

initial begin
repeat (100) begin
    @(posedge clk);
    #1;
    $display ("Time = %0t, LEDs = %b", $time, seg);
end
end
initial begin
    #9000;
   
    $finish;
end

endmodule

01.06/v.vcd
$date
	Thu Jun  1 09:58:20 2023
$end
$version
	Icarus Verilog
$end
$timescale
	1ps
$end
$scope module tb $end
$var wire 7 ! seg [6:0] $end
$var reg 1 " clk $end
$var reg 1 # rst $end
$scope module s $end
$var wire 1 $ button $end
$var wire 1 % change $end
$var wire 1 " clk $end
$var wire 1 # reset $end
$var wire 1 & rst $end
$var wire 1 ' button_out $end
$var reg 4 ( count [3:0] $end
$var reg 1 ) dff_1 $end
$var reg 1 * dff_2 $end
$var reg 7 + segOut [6:0] $end
$var reg 24 , timer [23:0] $end
$scope module debounce_i $end
$var wire 1 $ button $end
$var wire 1 ' button_out $end
$var wire 1 " clk $end
$var wire 1 & rst $end
$var wire 1 - full $end
$var wire 18 . counter_nxt [17:0] $end
$var reg 18 / counter [17:0] $end
$upscope $end
$upscope $end
$upscope $end
$enddefinitions $end
#0
$dumpvars
bx /
bx .
x-
b0 ,
b1000000 +
x*
x)
b0 (
x'
z&
x%
z$
1#
0"
b1000000 !
$end
#3000
1"
#6000
0"
#9000
1"
#10000
0#
#12000
0"
#15000
b1 ,
1"
#18000
0"
#21000
b10 ,
1"
#24000
0"
#27000
b11 ,
1"
#30000
0"
#33000
b100 ,
1"
#36000
0"
#39000
b101 ,
1"
#42000
0"
#45000
b110 ,
1"
#48000
0"
#51000
b111 ,
1"
#54000
0"
#57000
b1000 ,
1"
#60000
0"
#63000
b1001 ,
1"
#66000
0"
#69000
b1010 ,
1"
#72000
0"
#75000
b1011 ,
1"
#78000
0"
#81000
b1100 ,
1"
#84000
0"
#87000
b1111001 !
b1111001 +
b0 ,
b1 (
1"
#90000
0"
#93000
b1 ,
1"
#96000
0"
#99000
b10 ,
1"
#102000
0"
#105000
b11 ,
1"
#108000
0"
#111000
b100 ,
1"
#114000
0"
#117000
b101 ,
1"
#120000
0"
#123000
b110 ,
1"
#126000
0"
#129000
b111 ,
1"
#132000
0"
#135000
b1000 ,
1"
#138000
0"
#141000
b1001 ,
1"
#144000
0"
#147000
b1010 ,
1"
#150000
0"
#153000
b1011 ,
1"
#156000
0"
#159000
b1100 ,
1"
#162000
0"
#165000
b100100 !
b100100 +
b0 ,
b10 (
1"
#168000
0"
#171000
b1 ,
1"
#174000
0"
#177000
b10 ,
1"
#180000
0"
#183000
b11 ,
1"
#186000
0"
#189000
b100 ,
1"
#192000
0"
#195000
b101 ,
1"
#198000
0"
#201000
b110 ,
1"
#204000
0"
#207000
b111 ,
1"
#210000
0"
#213000
b1000 ,
1"
#216000
0"
#219000
b1001 ,
1"
#222000
0"
#225000
b1010 ,
1"
#228000
0"
#231000
b1011 ,
1"
#234000
0"
#237000
b1100 ,
1"
#240000
0"
#243000
b110000 !
b110000 +
b0 ,
b11 (
1"
#246000
0"
#249000
b1 ,
1"
#252000
0"
#255000
b10 ,
1"
#258000
0"
#261000
b11 ,
1"
#264000
0"
#267000
b100 ,
1"
#270000
0"
#273000
b101 ,
1"
#276000
0"
#279000
b110 ,
1"
#282000
0"
#285000
b111 ,
1"
#288000
0"
#291000
b1000 ,
1"
#294000
0"
#297000
b1001 ,
1"
#300000
0"
#303000
b1010 ,
1"
#306000
0"
#309000
b1011 ,
1"
#312000
0"
#315000
b1100 ,
1"
#318000
0"
#321000
b11001 !
b11001 +
b0 ,
b100 (
1"
#324000
0"
#327000
b1 ,
1"
#330000
0"
#333000
b10 ,
1"
#336000
0"
#339000
b11 ,
1"
#342000
0"
#345000
b100 ,
1"
#348000
0"
#351000
b101 ,
1"
#354000
0"
#357000
b110 ,
1"
#360000
0"
#363000
b111 ,
1"
#366000
0"
#369000
b1000 ,
1"
#372000
0"
#375000
b1001 ,
1"
#378000
0"
#381000
b1010 ,
1"
#384000
0"
#387000
b1011 ,
1"
#390000
0"
#393000
b1100 ,
1"
#396000
0"
#399000
b10010 !
b10010 +
b0 ,
b101 (
1"
#402000
0"
#405000
b1 ,
1"
#408000
0"
#411000
b10 ,
1"
#414000
0"
#417000
b11 ,
1"
#420000
0"
#423000
b100 ,
1"
#426000
0"
#429000
b101 ,
1"
#432000
0"
#435000
b110 ,
1"
#438000
0"
#441000
b111 ,
1"
#444000
0"
#447000
b1000 ,
1"
#450000
0"
#453000
b1001 ,
1"
#456000
0"
#459000
b1010 ,
1"
#462000
0"
#465000
b1011 ,
1"
#468000
0"
#471000
b1100 ,
1"
#474000
0"
#477000
b10 !
b10 +
b0 ,
b110 (
1"
#480000
0"
#483000
b1 ,
1"
#486000
0"
#489000
b10 ,
1"
#492000
0"
#495000
b11 ,
1"
#498000
0"
#501000
b100 ,
1"
#504000
0"
#507000
b101 ,
1"
#510000
0"
#513000
b110 ,
1"
#516000
0"
#519000
b111 ,
1"
#522000
0"
#525000
b1000 ,
1"
#528000
0"
#531000
b1001 ,
1"
#534000
0"
#537000
b1010 ,
1"
#540000
0"
#543000
b1011 ,
1"
#546000
0"
#549000
b1100 ,
1"
#552000
0"
#555000
b1111000 !
b1111000 +
b0 ,
b111 (
1"
#558000
0"
#561000
b1 ,
1"
#564000
0"
#567000
b10 ,
1"
#570000
0"
#573000
b11 ,
1"
#576000
0"
#579000
b100 ,
1"
#582000
0"
#585000
b101 ,
1"
#588000
0"
#591000
b110 ,
1"
#594000
0"
#597000
b111 ,
1"
#600000
0"
#603000
b1000 ,
1"
#606000
0"
#609000
b1001 ,
1"
#612000
0"
#615000
b1010 ,
1"
#618000
0"
#621000
b1011 ,
1"
#624000
0"
#627000
b1100 ,
1"
#630000
0"
#633000
b0 !
b0 +
b0 ,
b1000 (
1"
#636000
0"
#639000
b1 ,
1"
#642000
0"
#645000
b10 ,
1"
#648000
0"
#651000
b11 ,
1"
#654000
0"
#657000
b100 ,
1"
#660000
0"
#663000
b101 ,
1"
#666000
0"
#669000
b110 ,
1"
#672000
0"
#675000
b111 ,
1"
#678000
0"
#681000
b1000 ,
1"
#684000
0"
#687000
b1001 ,
1"
#690000
0"
#693000
b1010 ,
1"
#696000
0"
#699000
b1011 ,
1"
#702000
0"
#705000
b1100 ,
1"
#708000
0"
#711000
b10000 !
b10000 +
b0 ,
b1001 (
1"
#714000
0"
#717000
b1 ,
1"
#720000
0"
#723000
b10 ,
1"
#726000
0"
#729000
b11 ,
1"
#732000
0"
#735000
b100 ,
1"
#738000
0"
#741000
b101 ,
1"
#744000
0"
#747000
b110 ,
1"
#750000
0"
#753000
b111 ,
1"
#756000
0"
#759000
b1000 ,
1"
#762000
0"
#765000
b1001 ,
1"
#768000
0"
#771000
b1010 ,
1"
#774000
0"
#777000
b1011 ,
1"
#780000
0"
#783000
b1100 ,
1"
#786000
0"
#789000
b1111111 !
b1111111 +
b0 ,
b1010 (
1"
#792000
0"
#795000
b1 ,
1"
#798000
0"
#801000
b10 ,
1"
#804000
0"
#807000
b11 ,
1"
#810000
0"
#813000
b100 ,
1"
#816000
0"
#819000
b101 ,
1"
#822000
0"
#825000
b110 ,
1"
#828000
0"
#831000
b111 ,
1"
#834000
0"
#837000
b1000 ,
1"
#840000
0"
#843000
b1001 ,
1"
#846000
0"
#849000
b1010 ,
1"
#852000
0"
#855000
b1011 ,
1"
#858000
0"
#861000
b1100 ,
1"
#864000
0"
#867000
b0 ,
b1011 (
1"
#870000
0"
#873000
b1 ,
1"
#876000
0"
#879000
b10 ,
1"
#882000
0"
#885000
b11 ,
1"
#888000
0"
#891000
b100 ,
1"
#894000
0"
#897000
b101 ,
1"
#900000
0"
#903000
b110 ,
1"
#906000
0"
#909000
b111 ,
1"
#912000
0"
#915000
b1000 ,
1"
#918000
0"
#921000
b1001 ,
1"
#924000
0"
#927000
b1010 ,
1"
#930000
0"
#933000
b1011 ,
1"
#936000
0"
#939000
b1100 ,
1"
#942000
0"
#945000
b0 ,
b1100 (
1"
#948000
0"
#951000
b1 ,
1"
#954000
0"
#957000
b10 ,
1"
#960000
0"
#963000
b11 ,
1"
#966000
0"
#969000
b100 ,
1"
#972000
0"
#975000
b101 ,
1"
#978000
0"
#981000
b110 ,
1"
#984000
0"
#987000
b111 ,
1"
#990000
0"
#993000
b1000 ,
1"
#996000
0"
#999000
b1001 ,
1"
#1002000
0"
#1005000
b1010 ,
1"
#1008000
0"
#1011000
b1011 ,
1"
#1014000
0"
#1017000
b1100 ,
1"
#1020000
0"
#1023000
b0 ,
b1101 (
1"
#1026000
0"
#1029000
b1 ,
1"
#1032000
0"
#1035000
b10 ,
1"
#1038000
0"
#1041000
b11 ,
1"
#1044000
0"
#1047000
b100 ,
1"
#1050000
0"
#1053000
b101 ,
1"
#1056000
0"
#1059000
b110 ,
1"
#1062000
0"
#1065000
b111 ,
1"
#1068000
0"
#1071000
b1000 ,
1"
#1074000
0"
#1077000
b1001 ,
1"
#1080000
0"
#1083000
b1010 ,
1"
#1086000
0"
#1089000
b1011 ,
1"
#1092000
0"
#1095000
b1100 ,
1"
#1098000
0"
#1101000
b0 ,
b1110 (
1"
#1104000
0"
#1107000
b1 ,
1"
#1110000
0"
#1113000
b10 ,
1"
#1116000
0"
#1119000
b11 ,
1"
#1122000
0"
#1125000
b100 ,
1"
#1128000
0"
#1131000
b101 ,
1"
#1134000
0"
#1137000
b110 ,
1"
#1140000
0"
#1143000
b111 ,
1"
#1146000
0"
#1149000
b1000 ,
1"
#1152000
0"
#1155000
b1001 ,
1"
#1158000
0"
#1161000
b1010 ,
1"
#1164000
0"
#1167000
b1011 ,
1"
#1170000
0"
#1173000
b1100 ,
1"
#1176000
0"
#1179000
b0 ,
b1111 (
1"
#1182000
0"
#1185000
b1 ,
1"
#1188000
0"
#1191000
b10 ,
1"
#1194000
0"
#1197000
b11 ,
1"
#1200000
0"
#1203000
b100 ,
1"
#1206000
0"
#1209000
b101 ,
1"
#1212000
0"
#1215000
b110 ,
1"
#1218000
0"
#1221000
b111 ,
1"
#1224000
0"
#1227000
b1000 ,
1"
#1230000
0"
#1233000
b1001 ,
1"
#1236000
0"
#1239000
b1010 ,
1"
#1242000
0"
#1245000
b1011 ,
1"
#1248000
0"
#1251000
b1100 ,
1"
#1254000
0"
#1257000
b1000000 !
b1000000 +
b0 ,
b0 (
1"
#1260000
0"
#1263000
b1 ,
1"
#1266000
0"
#1269000
b10 ,
1"
#1272000
0"
#1275000
b11 ,
1"
#1278000
0"
#1281000
b100 ,
1"
#1284000
0"
#1287000
b101 ,
1"
#1290000
0"
#1293000
b110 ,
1"
#1296000
0"
#1299000
b111 ,
1"
#1302000
0"
#1305000
b1000 ,
1"
#1308000
0"
#1311000
b1001 ,
1"
#1314000
0"
#1317000
b1010 ,
1"
#1320000
0"
#1323000
b1011 ,
1"
#1326000
0"
#1329000
b1100 ,
1"
#1332000
0"
#1335000
b1111001 !
b1111001 +
b0 ,
b1 (
1"
#1338000
0"
#1341000
b1 ,
1"
#1344000
0"
#1347000
b10 ,
1"
#1350000
0"
#1353000
b11 ,
1"
#1356000
0"
#1359000
b100 ,
1"
#1362000
0"
#1365000
b101 ,
1"
#1368000
0"
#1371000
b110 ,
1"
#1374000
0"
#1377000
b111 ,
1"
#1380000
0"
#1383000
b1000 ,
1"
#1386000
0"
#1389000
b1001 ,
1"
#1392000
0"
#1395000
b1010 ,
1"
#1398000
0"
#1401000
b1011 ,
1"
#1404000
0"
#1407000
b1100 ,
1"
#1410000
0"
#1413000
b100100 !
b100100 +
b0 ,
b10 (
1"
#1416000
0"
#1419000
b1 ,
1"
#1422000
0"
#1425000
b10 ,
1"
#1428000
0"
#1431000
b11 ,
1"
#1434000
0"
#1437000
b100 ,
1"
#1440000
0"
#1443000
b101 ,
1"
#1446000
0"
#1449000
b110 ,
1"
#1452000
0"
#1455000
b111 ,
1"
#1458000
0"
#1461000
b1000 ,
1"
#1464000
0"
#1467000
b1001 ,
1"
#1470000
0"
#1473000
b1010 ,
1"
#1476000
0"
#1479000
b1011 ,
1"
#1482000
0"
#1485000
b1100 ,
1"
#1488000
0"
#1491000
b110000 !
b110000 +
b0 ,
b11 (
1"
#1494000
0"
#1497000
b1 ,
1"
#1500000
0"
#1503000
b10 ,
1"
#1506000
0"
#1509000
b11 ,
1"
#1512000
0"
#1515000
b100 ,
1"
#1518000
0"
#1521000
b101 ,
1"
#1524000
0"
#1527000
b110 ,
1"
#1530000
0"
#1533000
b111 ,
1"
#1536000
0"
#1539000
b1000 ,
1"
#1542000
0"
#1545000
b1001 ,
1"
#1548000
0"
#1551000
b1010 ,
1"
#1554000
0"
#1557000
b1011 ,
1"
#1560000
0"
#1563000
b1100 ,
1"
#1566000
0"
#1569000
b11001 !
b11001 +
b0 ,
b100 (
1"
#1572000
0"
#1575000
b1 ,
1"
#1578000
0"
#1581000
b10 ,
1"
#1584000
0"
#1587000
b11 ,
1"
#1590000
0"
#1593000
b100 ,
1"
#1596000
0"
#1599000
b101 ,
1"
#1602000
0"
#1605000
b110 ,
1"
#1608000
0"
#1611000
b111 ,
1"
#1614000
0"
#1617000
b1000 ,
1"
#1620000
0"
#1623000
b1001 ,
1"
#1626000
0"
#1629000
b1010 ,
1"
#1632000
0"
#1635000
b1011 ,
1"
#1638000
0"
#1641000
b1100 ,
1"
#1644000
0"
#1647000
b10010 !
b10010 +
b0 ,
b101 (
1"
#1650000
0"
#1653000
b1 ,
1"
#1656000
0"
#1659000
b10 ,
1"
#1662000
0"
#1665000
b11 ,
1"
#1668000
0"
#1671000
b100 ,
1"
#1674000
0"
#1677000
b101 ,
1"
#1680000
0"
#1683000
b110 ,
1"
#1686000
0"
#1689000
b111 ,
1"
#1692000
0"
#1695000
b1000 ,
1"
#1698000
0"
#1701000
b1001 ,
1"
#1704000
0"
#1707000
b1010 ,
1"
#1710000
0"
#1713000
b1011 ,
1"
#1716000
0"
#1719000
b1100 ,
1"
#1722000
0"
#1725000
b10 !
b10 +
b0 ,
b110 (
1"
#1728000
0"
#1731000
b1 ,
1"
#1734000
0"
#1737000
b10 ,
1"
#1740000
0"
#1743000
b11 ,
1"
#1746000
0"
#1749000
b100 ,
1"
#1752000
0"
#1755000
b101 ,
1"
#1758000
0"
#1761000
b110 ,
1"
#1764000
0"
#1767000
b111 ,
1"
#1770000
0"
#1773000
b1000 ,
1"
#1776000
0"
#1779000
b1001 ,
1"
#1782000
0"
#1785000
b1010 ,
1"
#1788000
0"
#1791000
b1011 ,
1"
#1794000
0"
#1797000
b1100 ,
1"
#1800000
0"
#1803000
b1111000 !
b1111000 +
b0 ,
b111 (
1"
#1806000
0"
#1809000
b1 ,
1"
#1812000
0"
#1815000
b10 ,
1"
#1818000
0"
#1821000
b11 ,
1"
#1824000
0"
#1827000
b100 ,
1"
#1830000
0"
#1833000
b101 ,
1"
#1836000
0"
#1839000
b110 ,
1"
#1842000
0"
#1845000
b111 ,
1"
#1848000
0"
#1851000
b1000 ,
1"
#1854000
0"
#1857000
b1001 ,
1"
#1860000
0"
#1863000
b1010 ,
1"
#1866000
0"
#1869000
b1011 ,
1"
#1872000
0"
#1875000
b1100 ,
1"
#1878000
0"
#1881000
b0 !
b0 +
b0 ,
b1000 (
1"
#1884000
0"
#1887000
b1 ,
1"
#1890000
0"
#1893000
b10 ,
1"
#1896000
0"
#1899000
b11 ,
1"
#1902000
0"
#1905000
b100 ,
1"
#1908000
0"
#1911000
b101 ,
1"
#1914000
0"
#1917000
b110 ,
1"
#1920000
0"
#1923000
b111 ,
1"
#1926000
0"
#1929000
b1000 ,
1"
#1932000
0"
#1935000
b1001 ,
1"
#1938000
0"
#1941000
b1010 ,
1"
#1944000
0"
#1947000
b1011 ,
1"
#1950000
0"
#1953000
b1100 ,
1"
#1956000
0"
#1959000
b10000 !
b10000 +
b0 ,
b1001 (
1"
#1962000
0"
#1965000
b1 ,
1"
#1968000
0"
#1971000
b10 ,
1"
#1974000
0"
#1977000
b11 ,
1"
#1980000
0"
#1983000
b100 ,
1"
#1986000
0"
#1989000
b101 ,
1"
#1992000
0"
#1995000
b110 ,
1"
#1998000
0"
#2001000
b111 ,
1"
#2004000
0"
#2007000
b1000 ,
1"
#2010000
0"
#2013000
b1001 ,
1"
#2016000
0"
#2019000
b1010 ,
1"
#2022000
0"
#2025000
b1011 ,
1"
#2028000
0"
#2031000
b1100 ,
1"
#2034000
0"
#2037000
b1111111 !
b1111111 +
b0 ,
b1010 (
1"
#2040000
0"
#2043000
b1 ,
1"
#2046000
0"
#2049000
b10 ,
1"
#2052000
0"
#2055000
b11 ,
1"
#2058000
0"
#2061000
b100 ,
1"
#2064000
0"
#2067000
b101 ,
1"
#2070000
0"
#2073000
b110 ,
1"
#2076000
0"
#2079000
b111 ,
1"
#2082000
0"
#2085000
b1000 ,
1"
#2088000
0"
#2091000
b1001 ,
1"
#2094000
0"
#2097000
b1010 ,
1"
#2100000
0"
#2103000
b1011 ,
1"
#2106000
0"
#2109000
b1100 ,
1"
#2112000
0"
#2115000
b0 ,
b1011 (
1"
#2118000
0"
#2121000
b1 ,
1"
#2124000
0"
#2127000
b10 ,
1"
#2130000
0"
#2133000
b11 ,
1"
#2136000
0"
#2139000
b100 ,
1"
#2142000
0"
#2145000
b101 ,
1"
#2148000
0"
#2151000
b110 ,
1"
#2154000
0"
#2157000
b111 ,
1"
#2160000
0"
#2163000
b1000 ,
1"
#2166000
0"
#2169000
b1001 ,
1"
#2172000
0"
#2175000
b1010 ,
1"
#2178000
0"
#2181000
b1011 ,
1"
#2184000
0"
#2187000
b1100 ,
1"
#2190000
0"
#2193000
b0 ,
b1100 (
1"
#2196000
0"
#2199000
b1 ,
1"
#2202000
0"
#2205000
b10 ,
1"
#2208000
0"
#2211000
b11 ,
1"
#2214000
0"
#2217000
b100 ,
1"
#2220000
0"
#2223000
b101 ,
1"
#2226000
0"
#2229000
b110 ,
1"
#2232000
0"
#2235000
b111 ,
1"
#2238000
0"
#2241000
b1000 ,
1"
#2244000
0"
#2247000
b1001 ,
1"
#2250000
0"
#2253000
b1010 ,
1"
#2256000
0"
#2259000
b1011 ,
1"
#2262000
0"
#2265000
b1100 ,
1"
#2268000
0"
#2271000
b0 ,
b1101 (
1"
#2274000
0"
#2277000
b1 ,
1"
#2280000
0"
#2283000
b10 ,
1"
#2286000
0"
#2289000
b11 ,
1"
#2292000
0"
#2295000
b100 ,
1"
#2298000
0"
#2301000
b101 ,
1"
#2304000
0"
#2307000
b110 ,
1"
#2310000
0"
#2313000
b111 ,
1"
#2316000
0"
#2319000
b1000 ,
1"
#2322000
0"
#2325000
b1001 ,
1"
#2328000
0"
#2331000
b1010 ,
1"
#2334000
0"
#2337000
b1011 ,
1"
#2340000
0"
#2343000
b1100 ,
1"
#2346000
0"
#2349000
b0 ,
b1110 (
1"
#2352000
0"
#2355000
b1 ,
1"
#2358000
0"
#2361000
b10 ,
1"
#2364000
0"
#2367000
b11 ,
1"
#2370000
0"
#2373000
b100 ,
1"
#2376000
0"
#2379000
b101 ,
1"
#2382000
0"
#2385000
b110 ,
1"
#2388000
0"
#2391000
b111 ,
1"
#2394000
0"
#2397000
b1000 ,
1"
#2400000
0"
#2403000
b1001 ,
1"
#2406000
0"
#2409000
b1010 ,
1"
#2412000
0"
#2415000
b1011 ,
1"
#2418000
0"
#2421000
b1100 ,
1"
#2424000
0"
#2427000
b0 ,
b1111 (
1"
#2430000
0"
#2433000
b1 ,
1"
#2436000
0"
#2439000
b10 ,
1"
#2442000
0"
#2445000
b11 ,
1"
#2448000
0"
#2451000
b100 ,
1"
#2454000
0"
#2457000
b101 ,
1"
#2460000
0"
#2463000
b110 ,
1"
#2466000
0"
#2469000
b111 ,
1"
#2472000
0"
#2475000
b1000 ,
1"
#2478000
0"
#2481000
b1001 ,
1"
#2484000
0"
#2487000
b1010 ,
1"
#2490000
0"
#2493000
b1011 ,
1"
#2496000
0"
#2499000
b1100 ,
1"
#2502000
0"
#2505000
b1000000 !
b1000000 +
b0 ,
b0 (
1"
#2508000
0"
#2511000
b1 ,
1"
#2514000
0"
#2517000
b10 ,
1"
#2520000
0"
#2523000
b11 ,
1"
#2526000
0"
#2529000
b100 ,
1"
#2532000
0"
#2535000
b101 ,
1"
#2538000
0"
#2541000
b110 ,
1"
#2544000
0"
#2547000
b111 ,
1"
#2550000
0"
#2553000
b1000 ,
1"
#2556000
0"
#2559000
b1001 ,
1"
#2562000
0"
#2565000
b1010 ,
1"
#2568000
0"
#2571000
b1011 ,
1"
#2574000
0"
#2577000
b1100 ,
1"
#2580000
0"
#2583000
b1111001 !
b1111001 +
b0 ,
b1 (
1"
#2586000
0"
#2589000
b1 ,
1"
#2592000
0"
#2595000
b10 ,
1"
#2598000
0"
#2601000
b11 ,
1"
#2604000
0"
#2607000
b100 ,
1"
#2610000
0"
#2613000
b101 ,
1"
#2616000
0"
#2619000
b110 ,
1"
#2622000
0"
#2625000
b111 ,
1"
#2628000
0"
#2631000
b1000 ,
1"
#2634000
0"
#2637000
b1001 ,
1"
#2640000
0"
#2643000
b1010 ,
1"
#2646000
0"
#2649000
b1011 ,
1"
#2652000
0"
#2655000
b1100 ,
1"
#2658000
0"
#2661000
b100100 !
b100100 +
b0 ,
b10 (
1"
#2664000
0"
#2667000
b1 ,
1"
#2670000
0"
#2673000
b10 ,
1"
#2676000
0"
#2679000
b11 ,
1"
#2682000
0"
#2685000
b100 ,
1"
#2688000
0"
#2691000
b101 ,
1"
#2694000
0"
#2697000
b110 ,
1"
#2700000
0"
#2703000
b111 ,
1"
#2706000
0"
#2709000
b1000 ,
1"
#2712000
0"
#2715000
b1001 ,
1"
#2718000
0"
#2721000
b1010 ,
1"
#2724000
0"
#2727000
b1011 ,
1"
#2730000
0"
#2733000
b1100 ,
1"
#2736000
0"
#2739000
b110000 !
b110000 +
b0 ,
b11 (
1"
#2742000
0"
#2745000
b1 ,
1"
#2748000
0"
#2751000
b10 ,
1"
#2754000
0"
#2757000
b11 ,
1"
#2760000
0"
#2763000
b100 ,
1"
#2766000
0"
#2769000
b101 ,
1"
#2772000
0"
#2775000
b110 ,
1"
#2778000
0"
#2781000
b111 ,
1"
#2784000
0"
#2787000
b1000 ,
1"
#2790000
0"
#2793000
b1001 ,
1"
#2796000
0"
#2799000
b1010 ,
1"
#2802000
0"
#2805000
b1011 ,
1"
#2808000
0"
#2811000
b1100 ,
1"
#2814000
0"
#2817000
b11001 !
b11001 +
b0 ,
b100 (
1"
#2820000
0"
#2823000
b1 ,
1"
#2826000
0"
#2829000
b10 ,
1"
#2832000
0"
#2835000
b11 ,
1"
#2838000
0"
#2841000
b100 ,
1"
#2844000
0"
#2847000
b101 ,
1"
#2850000
0"
#2853000
b110 ,
1"
#2856000
0"
#2859000
b111 ,
1"
#2862000
0"
#2865000
b1000 ,
1"
#2868000
0"
#2871000
b1001 ,
1"
#2874000
0"
#2877000
b1010 ,
1"
#2880000
0"
#2883000
b1011 ,
1"
#2886000
0"
#2889000
b1100 ,
1"
#2892000
0"
#2895000
b10010 !
b10010 +
b0 ,
b101 (
1"
#2898000
0"
#2901000
b1 ,
1"
#2904000
0"
#2907000
b10 ,
1"
#2910000
0"
#2913000
b11 ,
1"
#2916000
0"
#2919000
b100 ,
1"
#2922000
0"
#2925000
b101 ,
1"
#2928000
0"
#2931000
b110 ,
1"
#2934000
0"
#2937000
b111 ,
1"
#2940000
0"
#2943000
b1000 ,
1"
#2946000
0"
#2949000
b1001 ,
1"
#2952000
0"
#2955000
b1010 ,
1"
#2958000
0"
#2961000
b1011 ,
1"
#2964000
0"
#2967000
b1100 ,
1"
#2970000
0"
#2973000
b10 !
b10 +
b0 ,
b110 (
1"
#2976000
0"
#2979000
b1 ,
1"
#2982000
0"
#2985000
b10 ,
1"
#2988000
0"
#2991000
b11 ,
1"
#2994000
0"
#2997000
b100 ,
1"
#3000000
0"
#3003000
b101 ,
1"
#3006000
0"
#3009000
b110 ,
1"
#3012000
0"
#3015000
b111 ,
1"
#3018000
0"
#3021000
b1000 ,
1"
#3024000
0"
#3027000
b1001 ,
1"
#3030000
0"
#3033000
b1010 ,
1"
#3036000
0"
#3039000
b1011 ,
1"
#3042000
0"
#3045000
b1100 ,
1"
#3048000
0"
#3051000
b1111000 !
b1111000 +
b0 ,
b111 (
1"
#3054000
0"
#3057000
b1 ,
1"
#3060000
0"
#3063000
b10 ,
1"
#3066000
0"
#3069000
b11 ,
1"
#3072000
0"
#3075000
b100 ,
1"
#3078000
0"
#3081000
b101 ,
1"
#3084000
0"
#3087000
b110 ,
1"
#3090000
0"
#3093000
b111 ,
1"
#3096000
0"
#3099000
b1000 ,
1"
#3102000
0"
#3105000
b1001 ,
1"
#3108000
0"
#3111000
b1010 ,
1"
#3114000
0"
#3117000
b1011 ,
1"
#3120000
0"
#3123000
b1100 ,
1"
#3126000
0"
#3129000
b0 !
b0 +
b0 ,
b1000 (
1"
#3132000
0"
#3135000
b1 ,
1"
#3138000
0"
#3141000
b10 ,
1"
#3144000
0"
#3147000
b11 ,
1"
#3150000
0"
#3153000
b100 ,
1"
#3156000
0"
#3159000
b101 ,
1"
#3162000
0"
#3165000
b110 ,
1"
#3168000
0"
#3171000
b111 ,
1"
#3174000
0"
#3177000
b1000 ,
1"
#3180000
0"
#3183000
b1001 ,
1"
#3186000
0"
#3189000
b1010 ,
1"
#3192000
0"
#3195000
b1011 ,
1"
#3198000
0"
#3201000
b1100 ,
1"
#3204000
0"
#3207000
b10000 !
b10000 +
b0 ,
b1001 (
1"
#3210000
0"
#3213000
b1 ,
1"
#3216000
0"
#3219000
b10 ,
1"
#3222000
0"
#3225000
b11 ,
1"
#3228000
0"
#3231000
b100 ,
1"
#3234000
0"
#3237000
b101 ,
1"
#3240000
0"
#3243000
b110 ,
1"
#3246000
0"
#3249000
b111 ,
1"
#3252000
0"
#3255000
b1000 ,
1"
#3258000
0"
#3261000
b1001 ,
1"
#3264000
0"
#3267000
b1010 ,
1"
#3270000
0"
#3273000
b1011 ,
1"
#3276000
0"
#3279000
b1100 ,
1"
#3282000
0"
#3285000
b1111111 !
b1111111 +
b0 ,
b1010 (
1"
#3288000
0"
#3291000
b1 ,
1"
#3294000
0"
#3297000
b10 ,
1"
#3300000
0"
#3303000
b11 ,
1"
#3306000
0"
#3309000
b100 ,
1"
#3312000
0"
#3315000
b101 ,
1"
#3318000
0"
#3321000
b110 ,
1"
#3324000
0"
#3327000
b111 ,
1"
#3330000
0"
#3333000
b1000 ,
1"
#3336000
0"
#3339000
b1001 ,
1"
#3342000
0"
#3345000
b1010 ,
1"
#3348000
0"
#3351000
b1011 ,
1"
#3354000
0"
#3357000
b1100 ,
1"
#3360000
0"
#3363000
b0 ,
b1011 (
1"
#3366000
0"
#3369000
b1 ,
1"
#3372000
0"
#3375000
b10 ,
1"
#3378000
0"
#3381000
b11 ,
1"
#3384000
0"
#3387000
b100 ,
1"
#3390000
0"
#3393000
b101 ,
1"
#3396000
0"
#3399000
b110 ,
1"
#3402000
0"
#3405000
b111 ,
1"
#3408000
0"
#3411000
b1000 ,
1"
#3414000
0"
#3417000
b1001 ,
1"
#3420000
0"
#3423000
b1010 ,
1"
#3426000
0"
#3429000
b1011 ,
1"
#3432000
0"
#3435000
b1100 ,
1"
#3438000
0"
#3441000
b0 ,
b1100 (
1"
#3444000
0"
#3447000
b1 ,
1"
#3450000
0"
#3453000
b10 ,
1"
#3456000
0"
#3459000
b11 ,
1"
#3462000
0"
#3465000
b100 ,
1"
#3468000
0"
#3471000
b101 ,
1"
#3474000
0"
#3477000
b110 ,
1"
#3480000
0"
#3483000
b111 ,
1"
#3486000
0"
#3489000
b1000 ,
1"
#3492000
0"
